{"101": {"prod_name": "chocolate", "price": 10, "quantity": 197, "brand": "cadburry", "category": "chocolate"}, "102": {"prod_name": "soft drink", "price": 20, "quantity": 80, "brand": "coca-cola", "category": "bevarage"}, "103": {"prod_name": "Chips", "price": 15, "quantity": 200, "brand": "lays", "category": "snacks"}, "104": {"prod_name": "chocolate cake", "price": 500, "quantity": 10, "brand": "monginis", "category": "bakery"}, "105": {"prod_name": "cofee", "price": 40, "quantity": 100, "brand": "nes-cafe", "category": "bevarage"}, "106": {"prod_name": "almonds packet", "price": 200, "quantity": 50, "brand": "sofit", "category": "dry fruits"}, "107": {"prod_name": "milk chocolates", "price": 15, "quantity": 43, "brand": "milkibar", "category": "chocolate"}, "108": {"prod_name": "jelly", "price": 5, "quantity": 500, "brand": "jelly bites", "category": "candies"}, "109": {"prod_name": "fruit juice", "price": 40, "quantity": 50, "brand": "fruity", "category": "bevarage"}, "110": {"prod_name": "bread", "price": 30, "quantity": 17, "brand": "britania", "category": "bakery"}, "111": {"prod_name": "soyasticks", "price": 80, "quantity": 50, "brand": "haldiram", "category": "snacks"}, "112": {"prod_name": "mints", "price": 10, "quantity": 200, "brand": "mentos", "category": "candies"}, "113": {"prod_name": "coconut milk", "price": 45, "quantity": 30, "brand": "dabur", "category": "bevarage"}, "114": {"prod_name": "oreo biscuits", "price": 10, "quantity": 100, "brand": "oreo", "category": "biscuits"}, "115": {"prod_name": "dark chocolates", "price": 20, "quantity": 348, "brand": "bournville", "category": "chocolate"}, "116": {"prod_name": "berries", "price": 150, "quantity": 80, "brand": "berry", "category": "dry fruits"}, "117": {"prod_name": "peanuts", "price": 100, "quantity": 100, "brand": "dabur", "category": "dry fruits"}, "118": {"prod_name": "milk powder", "price": 40, "quantity": 25, "brand": "nestle", "category": "bakery"}, "119": {"prod_name": "maggy", "price": 12, "quantity": 249, "brand": "nestle", "category": "snacks"}, "120": {"prod_name": "lollipops", "price": 10, "quantity": 500, "brand": "popon", "category": "candies"}, "121": {"prod_name": "belgian chocolate", "price": 40, "quantity": 44, "brand": "walkers", "category": "chocolate"}, "122": {"prod_name": "milano", "price": 50, "quantity": 50, "brand": "parle", "category": "biscuits"}, "123": {"prod_name": "energy drinks", "price": 50, "quantity": 70, "brand": "gatorade", "category": "bevarage"}, "124": {"prod_name": "dates", "price": 50, "quantity": 100, "brand": "lion", "category": "dry fruits"}, "125": {"prod_name": "dryfruit chocolate", "price": 30, "quantity": 16, "brand": "britania", "cadburry": "chocolate"}, "126": {"prod_name": "fruit chews", "price": 10, "quantity": 50, "brand": "jolly", "category": "candies"}, "127": {"prod_name": "swiss chocolates", "price": 45, "quantity": 25, "brand": "lindt", "category": "chocolate"}, "128": {"prod_name": "mango juice", "price": 20, "quantity": 95, "brand": "slice", "category": "bevarage"}, "129": {"prod_name": "chocolate biscuits", "price": 20, "quantity": 200, "brand": "sunfeast", "category": "biscuits"}, "130": {"prod_name": "muffins", "price": 50, "quantity": 35, "brand": "little bites", "category": "bakery"}, "131": {"prod_name": "toffy", "price": 10, "quantity": 500, "brand": "eclairs", "category": "candies"}}